recviz/__init__.py
recviz/rec.py
recviz-0.0.4.dist-info/LICENSE
recviz-0.0.4.dist-info/METADATA
recviz-0.0.4.dist-info/WHEEL
recviz-0.0.4.dist-info/top_level.txt
recviz-0.0.4.dist-info/RECORD
